comp.py
compare_geoms/__init__.py
compare_geoms/data_loading.py
compare_geoms/main.py
compare_geoms/mol_graph_funcs.py
compare_geoms/molecule_processing.py
compare_geoms/py.typed
compare_geoms/examples/__init__.py
compare_geoms/examples/sample.py
compare_geoms-0.0.1.dist-info/LICENSE.md
compare_geoms-0.0.1.dist-info/METADATA
compare_geoms-0.0.1.dist-info/WHEEL
compare_geoms-0.0.1.dist-info/top_level.txt
compare_geoms-0.0.1.dist-info/RECORD
